{
  "generated_at": "2026-06-23T19:35:08.767231+09:00",
  "generated_at_ms": 1782210908767,
  "categories": {
    "econ": {
      "name": "경제 전반",
      "queries": [
        "경제뉴스",
        "경제전망",
        "한국경제"
      ],
      "news": [
        {
          "title": "'ABC+E' 추진 부서 만들고 '외로움돌봄국'은 해체 수순",
          "link": "https://www.kihoilbo.co.kr/news/articleView.html?idxno=3026875",
          "pubDate": "Tue, 23 Jun 2026 19:20:00 +0900",
          "pubTimestamp": 1782210000000,
          "sourceName": "KIHOILBO"
        },
        {
          "title": "머니무브 가속화에 저축은행 수신 경쟁 '후끈'…연 4% 예금 늘린다",
          "link": "https://www.thepublic.kr/news/articleView.html?idxno=308797",
          "pubDate": "Tue, 23 Jun 2026 19:18:00 +0900",
          "pubTimestamp": 1782209880000,
          "sourceName": "THEPUBLIC"
        },
        {
          "title": "\"농업용 면세유 지원 상한, 고유가 위기 땐 풀어줘야\"",
          "link": "https://www.agrinet.co.kr/news/articleView.html?idxno=405214",
          "pubDate": "Tue, 23 Jun 2026 19:04:00 +0900",
          "pubTimestamp": 1782209040000,
          "sourceName": "AGRINET"
        },
        {
          "title": "농업과 재외동포: 상생의 경제와 도덕적 성찰",
          "link": "https://www.agrinet.co.kr/news/articleView.html?idxno=405196",
          "pubDate": "Tue, 23 Jun 2026 19:04:00 +0900",
          "pubTimestamp": 1782209040000,
          "sourceName": "AGRINET"
        },
        {
          "title": "\"예약창 뜨자마자 마감\"…10배 싼 가격에 엄마들 몰려든 곳",
          "link": "https://www.hankyung.com/article/2026062335531",
          "pubDate": "Tue, 23 Jun 2026 19:01:00 +0900",
          "pubTimestamp": 1782208860000,
          "sourceName": "한국경제"
        },
        {
          "title": "韓 VS 남아공 승부 예측에 5억 원…월드컵 전체론 7.7조 몰렸다",
          "link": "https://www.sedaily.com/article/20059247?ref=naver",
          "pubDate": "Tue, 23 Jun 2026 18:56:00 +0900",
          "pubTimestamp": 1782208560000,
          "sourceName": "서울경제"
        },
        {
          "title": "[박정일 칼럼] 더 세진 규제 칼날, 기업하는 게 죄인가",
          "link": "https://www.dt.co.kr/article/12069130?ref=naver",
          "pubDate": "Tue, 23 Jun 2026 18:45:00 +0900",
          "pubTimestamp": 1782207900000,
          "sourceName": "DT"
        },
        {
          "title": "K3리그 5개 팀, K리그2 라이선스 취득 불발… 승강결정전 미개최",
          "link": "http://www.hansbiz.co.kr/news/articleView.html?idxno=846009",
          "pubDate": "Tue, 23 Jun 2026 18:38:00 +0900",
          "pubTimestamp": 1782207480000,
          "sourceName": "HANSBIZ"
        },
        {
          "title": "[K반도체 시총 쌍끌이 경쟁] '엎치락뒤치락' 삼성·하이닉스 시총 1위 경...",
          "link": "https://www.g-enews.com/view.php?ud=2026062316213377546ed0c62d49_1",
          "pubDate": "Tue, 23 Jun 2026 18:38:00 +0900",
          "pubTimestamp": 1782207480000,
          "sourceName": "G-ENEWS"
        },
        {
          "title": "코스피 9.99% 폭락... '공포는 공포를 불렀다'",
          "link": "https://www.ohmynews.com/NWS_Web/View/at_pg.aspx?CNTN_CD=A0003245720&CMPT_CD=P0010&utm_source=naver&utm_medium=newsearch&utm_campaign=naver_news",
          "pubDate": "Tue, 23 Jun 2026 18:36:00 +0900",
          "pubTimestamp": 1782207360000,
          "sourceName": "오마이뉴스"
        },
        {
          "title": "[외환-마감] 외인 대규모 주식 매도로 상승…2.10원↑",
          "link": "https://news.einfomax.co.kr/news/articleView.html?idxno=4421470",
          "pubDate": "Tue, 23 Jun 2026 18:34:00 +0900",
          "pubTimestamp": 1782207240000,
          "sourceName": "NEWS"
        },
        {
          "title": "[치솟는 국채금리] 전 구간 '4% 시대' 오나 …물가·AI發 '고금리 뉴노멀...",
          "link": "https://www.ajunews.com/view/20260623140920204",
          "pubDate": "Tue, 23 Jun 2026 18:32:00 +0900",
          "pubTimestamp": 1782207120000,
          "sourceName": "AJUNEWS"
        },
        {
          "title": "재경부, 결산체계개편 관련 국가회계 교육 실시",
          "link": "http://www.joseilbo.com/news/news_read.php?uid=570587&class=1&grp=",
          "pubDate": "Tue, 23 Jun 2026 18:32:00 +0900",
          "pubTimestamp": 1782207120000,
          "sourceName": "JOSEILBO"
        },
        {
          "title": "세계 최대 반도체 벨트… K칩 새 역사 짓는다",
          "link": "http://www.fnnews.com/news/202606231826477145",
          "pubDate": "Tue, 23 Jun 2026 18:28:00 +0900",
          "pubTimestamp": 1782206880000,
          "sourceName": "파이낸셜뉴스"
        },
        {
          "title": "브렉시트 이후 총리만 6명째…CNN \"영국 정치 불안의 원인은 경제\"",
          "link": "https://www.ajunews.com/view/20260623181539892",
          "pubDate": "Tue, 23 Jun 2026 18:24:00 +0900",
          "pubTimestamp": 1782206640000,
          "sourceName": "AJUNEWS"
        },
        {
          "title": "코스피 10% 폭락에 서킷브레이커…SK하이닉스, 종가 기준 시총 1위 수성",
          "link": "https://sateconomy.co.kr/news/view/1065596671211285",
          "pubDate": "Tue, 23 Jun 2026 18:20:00 +0900",
          "pubTimestamp": 1782206400000,
          "sourceName": "SATECONOMY"
        },
        {
          "title": "최저임금 수준 논의 돌입… 노동계 '12,000원' 주장에 경영계 '동결' 내...",
          "link": "http://worknworld.kctu.org/news/articleView.html?idxno=509506",
          "pubDate": "Tue, 23 Jun 2026 18:16:00 +0900",
          "pubTimestamp": 1782206160000,
          "sourceName": "WORKNWORLD"
        },
        {
          "title": "[단독] 에드워드 슐레진저 \"AI 사이클 매우 초기 단계…'광통신' 장기 성...",
          "link": "https://www.hankyung.com/article/2026062334761",
          "pubDate": "Tue, 23 Jun 2026 18:13:00 +0900",
          "pubTimestamp": 1782205980000,
          "sourceName": "한국경제"
        },
        {
          "title": "최저임금 협상 개시…노동계 '1만2000원' vs 경영계 '동결'",
          "link": "https://www.etnews.com/20260623000441",
          "pubDate": "Tue, 23 Jun 2026 18:12:00 +0900",
          "pubTimestamp": 1782205920000,
          "sourceName": "전자신문"
        },
        {
          "title": "[사설] 민생 실패에 무너진 英 스타머, 우리도 경고 새겨야",
          "link": "http://www.fnnews.com/news/202606231808410064",
          "pubDate": "Tue, 23 Jun 2026 18:11:00 +0900",
          "pubTimestamp": 1782205860000,
          "sourceName": "파이낸셜뉴스"
        },
        {
          "title": "[사설] 최저임금 논의, 벼랑 끝 자영업자 호소 귀 기울이길",
          "link": "http://www.fnnews.com/news/202606231808441090",
          "pubDate": "Tue, 23 Jun 2026 18:11:00 +0900",
          "pubTimestamp": 1782205860000,
          "sourceName": "파이낸셜뉴스"
        },
        {
          "title": "정년 65세 '청년' 해법은…\"상생기금 만들자\"",
          "link": "https://www.wowtv.co.kr/NewsCenter/News/Read?articleId=A202606230427&t=NNv",
          "pubDate": "Tue, 23 Jun 2026 18:06:00 +0900",
          "pubTimestamp": 1782205560000,
          "sourceName": "WOWTV"
        },
        {
          "title": "[머니무브] 4% 예금·10% 특판적금 등장…불장에 은행·저축은행 수신 경...",
          "link": "https://www.g-enews.com/view.php?ud=202606231442236885e30fcb1ba8_1",
          "pubDate": "Tue, 23 Jun 2026 18:02:00 +0900",
          "pubTimestamp": 1782205320000,
          "sourceName": "G-ENEWS"
        },
        {
          "title": "勞\"1만2천원\" 使 \"동결\"…최저임금 신경전",
          "link": "https://www.mk.co.kr/article/12081171",
          "pubDate": "Tue, 23 Jun 2026 18:01:00 +0900",
          "pubTimestamp": 1782205260000,
          "sourceName": "매일경제"
        },
        {
          "title": "양산상공회의소, 지식경제연구소 박종훈 소장 초청 CEO 조찬세미나",
          "link": "http://www.gndomin.com/news/articleView.html?idxno=479718",
          "pubDate": "Tue, 23 Jun 2026 17:52:00 +0900",
          "pubTimestamp": 1782204720000,
          "sourceName": "GNDOMIN"
        },
        {
          "title": "공기업도 전기료 경감 요구…전력 성수기 웃지 못하는 한전",
          "link": "https://www.pinpointnews.co.kr/news/articleView.html?idxno=462325",
          "pubDate": "Tue, 23 Jun 2026 17:46:00 +0900",
          "pubTimestamp": 1782204360000,
          "sourceName": "PINPOINTNEWS"
        },
        {
          "title": "대만 매체 \"테슬라 옵티머스 이르면 7월 생산\", 일부 협업사는 부품 공...",
          "link": "https://www.businesspost.co.kr/BP?command=article_view&num=440651",
          "pubDate": "Tue, 23 Jun 2026 17:42:00 +0900",
          "pubTimestamp": 1782204120000,
          "sourceName": "BUSINESSPOST"
        },
        {
          "title": "내년 최임임금 얼마?…노, 1만2000원 vs 사, 사실상 ‘동결’",
          "link": "http://www.worklaw.co.kr/view/view.asp?accessSite=Naver&accessMethod=Search&accessMenu=News&in_cate=124&in_cate2=0&gopage=1&bi_pidx=39313",
          "pubDate": "Tue, 23 Jun 2026 17:20:00 +0900",
          "pubTimestamp": 1782202800000,
          "sourceName": "WORKLAW"
        },
        {
          "title": "충북 소비자들 “경기 좋아질 것…지갑 열겠다”",
          "link": "http://www.inews24.com/view/1979044",
          "pubDate": "Tue, 23 Jun 2026 17:16:00 +0900",
          "pubTimestamp": 1782202560000,
          "sourceName": "INEWS24"
        },
        {
          "title": "농협 2차 개혁안 본격화…‘중앙회 권한 분산’ 쟁점",
          "link": "https://www.sentv.co.kr/article/view/sentv202606230067",
          "pubDate": "Tue, 23 Jun 2026 17:16:00 +0900",
          "pubTimestamp": 1782202560000,
          "sourceName": "SENTV"
        }
      ]
    },
    "stock": {
      "name": "주식/증시",
      "queries": [
        "코스피",
        "코스닥",
        "증시",
        "주식시장"
      ],
      "news": [
        {
          "title": "스페이스X, 개장 전 2%대 하락",
          "link": "https://news.einfomax.co.kr/news/articleView.html?idxno=4421477",
          "pubDate": "Tue, 23 Jun 2026 19:34:00 +0900",
          "pubTimestamp": 1782210840000,
          "sourceName": "NEWS"
        },
        {
          "title": "[기고]진주 창업정책, 이제는 우수한 창업기업들로 채워야",
          "link": "https://www.gnnews.co.kr/news/articleView.html?idxno=639632",
          "pubDate": "Tue, 23 Jun 2026 19:32:00 +0900",
          "pubTimestamp": 1782210720000,
          "sourceName": "GNNEWS"
        },
        {
          "title": "“2022년 9월 이후 최대 낙폭”…파랗게 질린 러시아 증시",
          "link": "https://www.mk.co.kr/article/12081261",
          "pubDate": "Tue, 23 Jun 2026 19:32:00 +0900",
          "pubTimestamp": 1782210720000,
          "sourceName": "매일경제"
        },
        {
          "title": "[아는기자]대통령 지지율 하락 두고…네 가지 딜레마?",
          "link": "https://www.ichannela.com/news/main/news_detailPage.do?publishId=000000536053",
          "pubDate": "Tue, 23 Jun 2026 19:30:00 +0900",
          "pubTimestamp": 1782210600000,
          "sourceName": "ICHANNELA"
        },
        {
          "title": "대만도 빚투 열풍…신용융자 1년새 160%↑",
          "link": "https://www.mt.co.kr/world/2026/06/23/2026062319142140073",
          "pubDate": "Tue, 23 Jun 2026 19:30:00 +0900",
          "pubTimestamp": 1782210600000,
          "sourceName": "머니투데이"
        },
        {
          "title": "[여적]대장주 교체",
          "link": "https://www.khan.co.kr/article/202606231929001",
          "pubDate": "Tue, 23 Jun 2026 19:29:00 +0900",
          "pubTimestamp": 1782210540000,
          "sourceName": "경향신문"
        },
        {
          "title": "‘삼전닉스 부자’ 늘어났나? 증권사, 초고액자산가 모시기 경쟁 ‘후끈...",
          "link": "https://www.munhwa.com/article/11597651?ref=naver",
          "pubDate": "Tue, 23 Jun 2026 19:28:00 +0900",
          "pubTimestamp": 1782210480000,
          "sourceName": "MUNHWA"
        },
        {
          "title": "이 대통령 “청년 소외감 뼈아프게 받아들여야”…민생·청년 집중 지지...",
          "link": "https://news.kbs.co.kr/news/pc/view/view.do?ncd=8593012&ref=A",
          "pubDate": "Tue, 23 Jun 2026 19:26:00 +0900",
          "pubTimestamp": 1782210360000,
          "sourceName": "KBS"
        },
        {
          "title": "코스피 또다시 8% 폭락, 서킷브레이커 발동",
          "link": "https://www.tokenpost.kr/news/market/372089",
          "pubDate": "Tue, 23 Jun 2026 19:24:00 +0900",
          "pubTimestamp": 1782210240000,
          "sourceName": "TOKENPOST"
        },
        {
          "title": "미래에셋증권, 모든 세대 아우르는 VIP 자산관리 경쟁력 부각 外",
          "link": "https://www.rcast.co.kr/news/articleView.html?idxno=31105",
          "pubDate": "Tue, 23 Jun 2026 19:24:00 +0900",
          "pubTimestamp": 1782210240000,
          "sourceName": "RCAST"
        },
        {
          "title": "2030 지지율 하락에…이 대통령 \"청년 소외감, 뼈아프게 받아들여야\"",
          "link": "http://www.mbn.co.kr/pages/news/newsView.php?news_seq_no=5201508",
          "pubDate": "Tue, 23 Jun 2026 19:23:00 +0900",
          "pubTimestamp": 1782210180000,
          "sourceName": "MBN"
        },
        {
          "title": "2030 지지율 적신호…이 대통령 “청년 소외 뼈아파”",
          "link": "https://www.ichannela.com/news/main/news_detailPage.do?publishId=000000536050",
          "pubDate": "Tue, 23 Jun 2026 19:22:00 +0900",
          "pubTimestamp": 1782210120000,
          "sourceName": "ICHANNELA"
        },
        {
          "title": "[亞증시-종합] 기술주發 차익실현 장세",
          "link": "https://news.einfomax.co.kr/news/articleView.html?idxno=4421475",
          "pubDate": "Tue, 23 Jun 2026 19:22:00 +0900",
          "pubTimestamp": 1782210120000,
          "sourceName": "NEWS"
        },
        {
          "title": "황성엽 금투협회장 \"개인투자 과열 우려…연금투자 활성화 필요\"",
          "link": "https://economist.co.kr/article/view/ecn202606230056",
          "pubDate": "Tue, 23 Jun 2026 19:22:00 +0900",
          "pubTimestamp": 1782210120000,
          "sourceName": "ECONOMIST"
        },
        {
          "title": "반도체 오르면 뭐하나...美 증시, 알파벳(GOOGL)·아마존(AMZN) 추락에 '휘...",
          "link": "http://coinreaders.com/243985",
          "pubDate": "Tue, 23 Jun 2026 19:22:00 +0900",
          "pubTimestamp": 1782210120000,
          "sourceName": "COINREADERS"
        },
        {
          "title": "[이슈플러스] '검은 화요일' 코스피 10%대 가까이 폭락...원인은?",
          "link": "https://www.ytn.co.kr/_ln/0102_202606231921468037",
          "pubDate": "Tue, 23 Jun 2026 19:21:00 +0900",
          "pubTimestamp": 1782210060000,
          "sourceName": "YTN"
        },
        {
          "title": "[사설] ‘코스피발’ 자산 양극화, 정부의 해소 대책 시급하다",
          "link": "http://www.kookje.co.kr/news2011/asp/newsbody.asp?code=1700&key=20260624.22019006785",
          "pubDate": "Tue, 23 Jun 2026 19:19:00 +0900",
          "pubTimestamp": 1782209940000,
          "sourceName": "KOOKJE"
        },
        {
          "title": "머니무브 가속화에 저축은행 수신 경쟁 '후끈'…연 4% 예금 늘린다",
          "link": "https://www.thepublic.kr/news/articleView.html?idxno=308797",
          "pubDate": "Tue, 23 Jun 2026 19:18:00 +0900",
          "pubTimestamp": 1782209880000,
          "sourceName": "THEPUBLIC"
        },
        {
          "title": "[급등락주 짚어보기] 역대급 패닉장 속 반도체·바이오 틈새 호재...차A...",
          "link": "https://www.etoday.co.kr/news/view/2596514",
          "pubDate": "Tue, 23 Jun 2026 19:18:00 +0900",
          "pubTimestamp": 1782209880000,
          "sourceName": "ETODAY"
        },
        {
          "title": "국민연금의 '혁신'…카카오 손잡고 AI 대전환, 내년엔 청년 보험료 지원",
          "link": "https://www.thepublic.kr/news/articleView.html?idxno=308799",
          "pubDate": "Tue, 23 Jun 2026 19:18:00 +0900",
          "pubTimestamp": 1782209880000,
          "sourceName": "THEPUBLIC"
        },
        {
          "title": "국민연금공단, 2025년 공공기관 경영평가 'A등급'…사상 첫 2년 연속",
          "link": "https://www.thepublic.kr/news/articleView.html?idxno=308798",
          "pubDate": "Tue, 23 Jun 2026 19:18:00 +0900",
          "pubTimestamp": 1782209880000,
          "sourceName": "THEPUBLIC"
        },
        {
          "title": "국민연금 코스피 60조 매도 현실화하나…김성주 이사장 \"시장 충격 최소...",
          "link": "http://www.mbn.co.kr/pages/news/newsView.php?news_seq_no=5201507",
          "pubDate": "Tue, 23 Jun 2026 19:15:00 +0900",
          "pubTimestamp": 1782209700000,
          "sourceName": "MBN"
        },
        {
          "title": "이 대통령 “반도체 호황 이면에 짙은 양극화 그늘”",
          "link": "http://www.jndn.com/article.php?aid=1782209482434857093",
          "pubDate": "Tue, 23 Jun 2026 19:14:00 +0900",
          "pubTimestamp": 1782209640000,
          "sourceName": "JNDN"
        },
        {
          "title": "코스피 '검은 화요일'...외국인·기관 투매로 역대 최대 910.71포인트 하...",
          "link": "https://www.livebiz.today/news/articleView.html?idxno=202817",
          "pubDate": "Tue, 23 Jun 2026 19:14:00 +0900",
          "pubTimestamp": 1782209640000,
          "sourceName": "LIVEBIZ"
        },
        {
          "title": "반도체 차익실현에 10% 역대 최대 폭락…코스닥도 ‘뚝’(종합)",
          "link": "http://www.kookje.co.kr/news2011/asp/newsbody.asp?code=0200&key=20260624.22010007082",
          "pubDate": "Tue, 23 Jun 2026 19:12:00 +0900",
          "pubTimestamp": 1782209520000,
          "sourceName": "KOOKJE"
        },
        {
          "title": "반도체 ‘매물 폭탄’에 8% 급락…역대급 변동성",
          "link": "https://news.kbs.co.kr/news/pc/view/view.do?ncd=8592979&ref=A",
          "pubDate": "Tue, 23 Jun 2026 19:12:00 +0900",
          "pubTimestamp": 1782209520000,
          "sourceName": "KBS"
        },
        {
          "title": "1만피 눈앞서 '와르르'…코스피 역대 최대 910p 급락",
          "link": "http://www.mbn.co.kr/pages/news/newsView.php?news_seq_no=5201515",
          "pubDate": "Tue, 23 Jun 2026 19:09:00 +0900",
          "pubTimestamp": 1782209340000,
          "sourceName": "MBN"
        },
        {
          "title": "코스피 울린 국민연금 리밸런싱…5일간 1.5조 팔았다",
          "link": "https://www.newsquest.co.kr/news/articleView.html?idxno=268405",
          "pubDate": "Tue, 23 Jun 2026 19:08:00 +0900",
          "pubTimestamp": 1782209280000,
          "sourceName": "NEWSQUEST"
        },
        {
          "title": "빗썸 지주사 얽힌 비덴트·버킷스튜디오 또 상폐 위기…소액주주 반발",
          "link": "https://www.bizhankook.com/bk/article/32598",
          "pubDate": "Tue, 23 Jun 2026 19:06:00 +0900",
          "pubTimestamp": 1782209160000,
          "sourceName": "BIZHANKOOK"
        },
        {
          "title": "내년도 최저임금 최초 요구안… 勞 “1만2000원” vs 使 “동결”",
          "link": "https://www.kmib.co.kr/article/view.asp?arcid=1782204971&code=11131800&cp=nv",
          "pubDate": "Tue, 23 Jun 2026 19:05:00 +0900",
          "pubTimestamp": 1782209100000,
          "sourceName": "국민일보"
        }
      ]
    },
    "real": {
      "name": "부동산",
      "queries": [
        "부동산시장",
        "아파트 매매",
        "집값",
        "전세값",
        "분양"
      ],
      "news": [
        {
          "title": "경실련 \"이재명 정부, 전월세시장 불안 심화 정책 중단해야\"",
          "link": "https://www.pressian.com/pages/articles/2026062317301753652?utm_source=naver&utm_medium=search",
          "pubDate": "Tue, 23 Jun 2026 19:30:00 +0900",
          "pubTimestamp": 1782210600000,
          "sourceName": "PRESSIAN"
        },
        {
          "title": "[아는기자]대통령 지지율 하락 두고…네 가지 딜레마?",
          "link": "https://www.ichannela.com/news/main/news_detailPage.do?publishId=000000536053",
          "pubDate": "Tue, 23 Jun 2026 19:30:00 +0900",
          "pubTimestamp": 1782210600000,
          "sourceName": "ICHANNELA"
        },
        {
          "title": "‘삼전닉스 부자’ 늘어났나? 증권사, 초고액자산가 모시기 경쟁 ‘후끈...",
          "link": "https://www.munhwa.com/article/11597651?ref=naver",
          "pubDate": "Tue, 23 Jun 2026 19:28:00 +0900",
          "pubTimestamp": 1782210480000,
          "sourceName": "MUNHWA"
        },
        {
          "title": "아파트라는 ‘기성복’을 가족의 ‘맞춤복’으로 수선하는 법",
          "link": "https://www.hani.co.kr/arti/opinion/column/1264982.html",
          "pubDate": "Tue, 23 Jun 2026 19:28:00 +0900",
          "pubTimestamp": 1782210480000,
          "sourceName": "한겨레"
        },
        {
          "title": "[이슈] 한성숙 청문회 D-2, 정보유출·다주택 논란 격돌…여야 '지명철회...",
          "link": "https://www.polinews.co.kr/news/articleView.html?idxno=734897",
          "pubDate": "Tue, 23 Jun 2026 19:27:00 +0900",
          "pubTimestamp": 1782210420000,
          "sourceName": "POLINEWS"
        },
        {
          "title": "[건설소식] 롯데건설·현대건설·대우건설",
          "link": "https://sports.hankooki.com/news/articleView.html?idxno=6935254",
          "pubDate": "Tue, 23 Jun 2026 19:24:00 +0900",
          "pubTimestamp": 1782210240000,
          "sourceName": "SPORTS"
        },
        {
          "title": "[이슈플러스] '검은 화요일' 코스피 10%대 가까이 폭락...원인은?",
          "link": "https://www.ytn.co.kr/_ln/0102_202606231921468037",
          "pubDate": "Tue, 23 Jun 2026 19:21:00 +0900",
          "pubTimestamp": 1782210060000,
          "sourceName": "YTN"
        },
        {
          "title": "[사설] ‘코스피발’ 자산 양극화, 정부의 해소 대책 시급하다",
          "link": "http://www.kookje.co.kr/news2011/asp/newsbody.asp?code=1700&key=20260624.22019006785",
          "pubDate": "Tue, 23 Jun 2026 19:19:00 +0900",
          "pubTimestamp": 1782209940000,
          "sourceName": "KOOKJE"
        },
        {
          "title": "[단독]광주 동구 해원정사 봉안당 불법 운영 의혹",
          "link": "https://www.namdonews.com/news/articleView.html?idxno=914581",
          "pubDate": "Tue, 23 Jun 2026 19:16:00 +0900",
          "pubTimestamp": 1782209760000,
          "sourceName": "NAMDONEWS"
        },
        {
          "title": "[단독] “하나자산신탁이 내 명의 계약서 공개 거부”… ‘300억 분양계...",
          "link": "https://www.kmib.co.kr/article/view.asp?arcid=0030010103&code=61121111&cp=nv",
          "pubDate": "Tue, 23 Jun 2026 19:08:00 +0900",
          "pubTimestamp": 1782209280000,
          "sourceName": "국민일보"
        },
        {
          "title": "[전남연구원 시군 정책보고서] (4)나주-\"에너지 수도 넘어 20만 과학도시...",
          "link": "https://www.namdonews.com/news/articleView.html?idxno=914552",
          "pubDate": "Tue, 23 Jun 2026 19:08:00 +0900",
          "pubTimestamp": 1782209280000,
          "sourceName": "NAMDONEWS"
        },
        {
          "title": "[사설] 집값 오르는 반도체 특수, 추락하는 상권 외면 안된다",
          "link": "https://www.joongboo.com/news/articleView.html?idxno=363729521",
          "pubDate": "Tue, 23 Jun 2026 19:06:00 +0900",
          "pubTimestamp": 1782209160000,
          "sourceName": "JOONGBOO"
        },
        {
          "title": "인천 송도 입주 절벽에 전·월세 급등 기업 종사자·청년 주거난 심각",
          "link": "https://www.kihoilbo.co.kr/news/articleView.html?idxno=3026874",
          "pubDate": "Tue, 23 Jun 2026 19:04:00 +0900",
          "pubTimestamp": 1782209040000,
          "sourceName": "KIHOILBO"
        },
        {
          "title": "전북농기원, 천적 농업 활성화 세미나 개최",
          "link": "https://www.agrinet.co.kr/news/articleView.html?idxno=405165",
          "pubDate": "Tue, 23 Jun 2026 19:04:00 +0900",
          "pubTimestamp": 1782209040000,
          "sourceName": "AGRINET"
        },
        {
          "title": "[르포] 원전 유치, 영덕에 다시 희망이 움튼다",
          "link": "https://www.kbmaeil.com/article/20260622500090",
          "pubDate": "Tue, 23 Jun 2026 19:02:00 +0900",
          "pubTimestamp": 1782208920000,
          "sourceName": "KBMAEIL"
        },
        {
          "title": "집값 비싼데 가성비 주택 찾자... 30대, 경매 시장에서도 '큰손'",
          "link": "https://www.hankookilbo.com/news/article/A2026062313380004571?did=NA",
          "pubDate": "Tue, 23 Jun 2026 19:01:00 +0900",
          "pubTimestamp": 1782208860000,
          "sourceName": "HANKOOKILBO"
        },
        {
          "title": "인천시, 5월 주택시장 매매 하락세 지속… 전세가격은 상승",
          "link": "http://www.lawissue.co.kr/view.php?ud=202606231109187363d94aa4ada6_12",
          "pubDate": "Tue, 23 Jun 2026 18:58:00 +0900",
          "pubTimestamp": 1782208680000,
          "sourceName": "LAWISSUE"
        },
        {
          "title": "국제유가 하락에도 집값은 '제자리 전망'…분양가 인하 기대 낮아",
          "link": "https://www.daejonilbo.com/news/articleView.html?idxno=2283450",
          "pubDate": "Tue, 23 Jun 2026 18:58:00 +0900",
          "pubTimestamp": 1782208680000,
          "sourceName": "DAEJONILBO"
        },
        {
          "title": "한성숙, 청문회 이틀 남기고 ‘1주택자’로",
          "link": "https://www.segye.com/newsView/20260623515079?OutUrl=naver",
          "pubDate": "Tue, 23 Jun 2026 18:55:00 +0900",
          "pubTimestamp": 1782208500000,
          "sourceName": "SEGYE"
        },
        {
          "title": "[더in터뷰] 집값 '들썩' 동탄에 무슨 일이? \"삼전닉스 세권 '오버슈팅' ...",
          "link": "https://news.jtbc.co.kr/article/NB12304635?influxDiv=NAVER",
          "pubDate": "Tue, 23 Jun 2026 18:54:00 +0900",
          "pubTimestamp": 1782208440000,
          "sourceName": "NEWS"
        },
        {
          "title": "[이번 주 분양 시장] 분당 신혼희망타운·노량진 하이엔드·고덕 대단지...",
          "link": "http://www.ftoday.co.kr/news/articleView.html?idxno=360954",
          "pubDate": "Tue, 23 Jun 2026 18:50:00 +0900",
          "pubTimestamp": 1782208200000,
          "sourceName": "FTODAY"
        },
        {
          "title": "한성숙, 주택 2채 추가 처분해 1주택자로…“취득가보다 낮게 팔아”",
          "link": "https://www.donga.com/news/Politics/article/all/20260623/134166587/1",
          "pubDate": "Tue, 23 Jun 2026 18:49:00 +0900",
          "pubTimestamp": 1782208140000,
          "sourceName": "동아일보"
        },
        {
          "title": "반도체 기대감 반영…들썩이는 광주·전남 자산시장",
          "link": "http://www.kwangju.co.kr/article.php?aid=1782207900800458005",
          "pubDate": "Tue, 23 Jun 2026 18:48:00 +0900",
          "pubTimestamp": 1782208080000,
          "sourceName": "KWANGJU"
        },
        {
          "title": "“초고가 펜트하우스, 대출 없이 현금으로 샀다”…구매자 60% 육박한다...",
          "link": "https://biz.heraldcorp.com/article/10785706?ref=naver",
          "pubDate": "Tue, 23 Jun 2026 18:46:00 +0900",
          "pubTimestamp": 1782207960000,
          "sourceName": "헤럴드경제"
        },
        {
          "title": "서울 등록임대 4만가구 '흔들'…세제개편에 임대차 시장 긴장 '[Only 이데...",
          "link": "https://www.edaily.co.kr/news/newspath.asp?newsid=05274246645484672",
          "pubDate": "Tue, 23 Jun 2026 18:42:00 +0900",
          "pubTimestamp": 1782207720000,
          "sourceName": "이데일리"
        },
        {
          "title": "[여명] 누가 청년의 ‘광장’을 가로채려 하나",
          "link": "https://www.sedaily.com/article/20059241?ref=naver",
          "pubDate": "Tue, 23 Jun 2026 18:42:00 +0900",
          "pubTimestamp": 1782207720000,
          "sourceName": "서울경제"
        },
        {
          "title": "‘전세 종말’ 대출규제 고민해야 [기자의눈]",
          "link": "https://www.sedaily.com/article/20059239?ref=naver",
          "pubDate": "Tue, 23 Jun 2026 18:41:00 +0900",
          "pubTimestamp": 1782207660000,
          "sourceName": "서울경제"
        },
        {
          "title": "현대건설, 고덕에 2122가구 '힐스테이트 고덕엘리스트' 7월 분양",
          "link": "https://www.webeconomy.co.kr/news/articleView.html?idxno=2209509",
          "pubDate": "Tue, 23 Jun 2026 18:40:00 +0900",
          "pubTimestamp": 1782207600000,
          "sourceName": "WEBECONOMY"
        },
        {
          "title": "[르포] 선전은 여전히 '해방 전쟁중'···항일 유격대 DNA 계승 개혁개...",
          "link": "http://www.hellodd.com/news/articleView.html?idxno=112220",
          "pubDate": "Tue, 23 Jun 2026 18:38:00 +0900",
          "pubTimestamp": 1782207480000,
          "sourceName": "HELLODD"
        },
        {
          "title": "[아파트 경매] 대전 도마동 효성타운 1억 6,590만 원",
          "link": "https://www.newstnt.com/news/articleView.html?idxno=707508",
          "pubDate": "Tue, 23 Jun 2026 18:34:00 +0900",
          "pubTimestamp": 1782207240000,
          "sourceName": "NEWSTNT"
        }
      ]
    },
    "global": {
      "name": "글로벌",
      "queries": [
        "FOMC",
        "미국 증시",
        "다우존스",
        "나스닥",
        "국제유가",
        "중국 GDP",
        "일본은행"
      ],
      "news": [
        {
          "title": "“2022년 9월 이후 최대 낙폭”…파랗게 질린 러시아 증시",
          "link": "https://www.mk.co.kr/article/12081261",
          "pubDate": "Tue, 23 Jun 2026 19:32:00 +0900",
          "pubTimestamp": 1782210720000,
          "sourceName": "매일경제"
        },
        {
          "title": "고유가가 살린 폭스바겐…전기차 판매 호조에 회복세",
          "link": "https://www.ekn.kr/web/view.php?key=20260623026515748",
          "pubDate": "Tue, 23 Jun 2026 19:30:00 +0900",
          "pubTimestamp": 1782210600000,
          "sourceName": "EKN"
        },
        {
          "title": "[여적]대장주 교체",
          "link": "https://www.khan.co.kr/article/202606231929001",
          "pubDate": "Tue, 23 Jun 2026 19:29:00 +0900",
          "pubTimestamp": 1782210540000,
          "sourceName": "경향신문"
        },
        {
          "title": "반도체 오르면 뭐하나...美 증시, 알파벳(GOOGL)·아마존(AMZN) 추락에 '휘...",
          "link": "http://coinreaders.com/243985",
          "pubDate": "Tue, 23 Jun 2026 19:22:00 +0900",
          "pubTimestamp": 1782210120000,
          "sourceName": "COINREADERS"
        },
        {
          "title": "\"연준, 올해 금리 3차례 인상 가능\"…달라진 월가 전망",
          "link": "https://www.newsis.com/view/NISX20260623_0003680690",
          "pubDate": "Tue, 23 Jun 2026 19:20:00 +0900",
          "pubTimestamp": 1782210000000,
          "sourceName": "뉴시스"
        },
        {
          "title": "스페이스X, 사상 최대 IPO 직후 주가 흔들…16% 급락",
          "link": "https://www.newsis.com/view/NISX20260623_0003680684",
          "pubDate": "Tue, 23 Jun 2026 19:16:00 +0900",
          "pubTimestamp": 1782209760000,
          "sourceName": "뉴시스"
        },
        {
          "title": "일본은 어떻게 반등했나?…산업 대전환에 나선 영국",
          "link": "https://news.kbs.co.kr/news/pc/view/view.do?ncd=8592972&ref=A",
          "pubDate": "Tue, 23 Jun 2026 19:10:00 +0900",
          "pubTimestamp": 1782209400000,
          "sourceName": "KBS"
        },
        {
          "title": "\"농업용 면세유 지원 상한, 고유가 위기 땐 풀어줘야\"",
          "link": "https://www.agrinet.co.kr/news/articleView.html?idxno=405214",
          "pubDate": "Tue, 23 Jun 2026 19:04:00 +0900",
          "pubTimestamp": 1782209040000,
          "sourceName": "AGRINET"
        },
        {
          "title": "[최남주의 비즈토크] 시총 742조 증발한 날 빚투는 사상 최대",
          "link": "https://www.seoultimes.news/news/article.html?no=2000096953",
          "pubDate": "Tue, 23 Jun 2026 19:02:00 +0900",
          "pubTimestamp": 1782208920000,
          "sourceName": "SEOULTIMES"
        },
        {
          "title": "스페이스X(SPCX), 고점서 25% 폭락...투매 폭탄 속 추가 하락 경고등",
          "link": "http://coinreaders.com/243981",
          "pubDate": "Tue, 23 Jun 2026 19:02:00 +0900",
          "pubTimestamp": 1782208920000,
          "sourceName": "COINREADERS"
        },
        {
          "title": "[초점] 시총 역전 다음날 역대급 폭락…'강세장 종료 시그널' 재조명",
          "link": "http://www.newsian.co.kr/news/articleView.html?idxno=91343",
          "pubDate": "Tue, 23 Jun 2026 19:00:00 +0900",
          "pubTimestamp": 1782208800000,
          "sourceName": "NEWSIAN"
        },
        {
          "title": "국제유가 하락에도 집값은 '제자리 전망'…분양가 인하 기대 낮아",
          "link": "https://www.daejonilbo.com/news/articleView.html?idxno=2283450",
          "pubDate": "Tue, 23 Jun 2026 18:58:00 +0900",
          "pubTimestamp": 1782208680000,
          "sourceName": "DAEJONILBO"
        },
        {
          "title": "김정관 \"EU 철강 무관세쿼터 긍정 합의… 46％까진 안 줄이기로\"",
          "link": "https://www.dt.co.kr/article/12069133?ref=naver",
          "pubDate": "Tue, 23 Jun 2026 18:51:00 +0900",
          "pubTimestamp": 1782208260000,
          "sourceName": "DT"
        },
        {
          "title": "[채권-마감] 주가 급락에 위험회피 심리…국고 3년 4.0bp↓",
          "link": "https://news.einfomax.co.kr/news/articleView.html?idxno=4421471",
          "pubDate": "Tue, 23 Jun 2026 18:44:00 +0900",
          "pubTimestamp": 1782207840000,
          "sourceName": "NEWS"
        },
        {
          "title": "“이러다 공모가까지 가겠네” 스페이스X 급락에 울상…3조원이나 폭풍...",
          "link": "https://biz.heraldcorp.com/article/10784896?ref=naver",
          "pubDate": "Tue, 23 Jun 2026 18:41:00 +0900",
          "pubTimestamp": 1782207660000,
          "sourceName": "헤럴드경제"
        },
        {
          "title": "국제유가, 美-이란 종전 협상 진전에 하락…브렌트 3%·WTI 2%↓",
          "link": "https://www.industrynews.co.kr/news/articleView.html?idxno=82482",
          "pubDate": "Tue, 23 Jun 2026 18:40:00 +0900",
          "pubTimestamp": 1782207600000,
          "sourceName": "INDUSTRYNEWS"
        },
        {
          "title": "[K반도체 시총 쌍끌이 경쟁] '엎치락뒤치락' 삼성·하이닉스 시총 1위 경...",
          "link": "https://www.g-enews.com/view.php?ud=2026062316213377546ed0c62d49_1",
          "pubDate": "Tue, 23 Jun 2026 18:38:00 +0900",
          "pubTimestamp": 1782207480000,
          "sourceName": "G-ENEWS"
        },
        {
          "title": "[인천 행정개편으로 돌아보는 역사] 편입 37년 만의 분구 영종구의 탄생",
          "link": "https://www.kihoilbo.co.kr/news/articleView.html?idxno=3026830",
          "pubDate": "Tue, 23 Jun 2026 18:34:00 +0900",
          "pubTimestamp": 1782207240000,
          "sourceName": "KIHOILBO"
        },
        {
          "title": "[치솟는 국채금리] 전 구간 '4% 시대' 오나 …물가·AI發 '고금리 뉴노멀...",
          "link": "https://www.ajunews.com/view/20260623140920204",
          "pubDate": "Tue, 23 Jun 2026 18:32:00 +0900",
          "pubTimestamp": 1782207120000,
          "sourceName": "AJUNEWS"
        },
        {
          "title": "국제유가 하락에도 전북 기름값 2천원대, 시민 부담 지속",
          "link": "http://www.domin.co.kr/news/articleView.html?idxno=1559551",
          "pubDate": "Tue, 23 Jun 2026 18:32:00 +0900",
          "pubTimestamp": 1782207120000,
          "sourceName": "DOMIN"
        },
        {
          "title": "\"수수료보다 수익률\"…헤지펀드 DNA 통했다",
          "link": "https://www.hankyung.com/article/2026062335451",
          "pubDate": "Tue, 23 Jun 2026 18:27:00 +0900",
          "pubTimestamp": 1782206820000,
          "sourceName": "한국경제"
        },
        {
          "title": "타임폴리오, TIME ETF 순자산 10조 돌파",
          "link": "https://www.mt.co.kr/stock/2026/06/23/2026062318214852024",
          "pubDate": "Tue, 23 Jun 2026 18:27:00 +0900",
          "pubTimestamp": 1782206820000,
          "sourceName": "머니투데이"
        },
        {
          "title": "美 증시, 기술주 고평가에 개장 전 줄줄이 하락...글로벌 동반 폭락장 오...",
          "link": "http://coinreaders.com/243972",
          "pubDate": "Tue, 23 Jun 2026 18:26:00 +0900",
          "pubTimestamp": 1782206760000,
          "sourceName": "COINREADERS"
        },
        {
          "title": "이르면 다음주 석유 최고가격 내릴 듯…유류세 인하 확대는 8월부터",
          "link": "https://www.hani.co.kr/arti/economy/economy_general/1264972.html",
          "pubDate": "Tue, 23 Jun 2026 18:24:00 +0900",
          "pubTimestamp": 1782206640000,
          "sourceName": "한겨레"
        },
        {
          "title": "닛케이, 7만 2000선 안착 시도… AI·반도체가 끌고 '슈퍼 엔저'가 밀었...",
          "link": "https://www.g-enews.com/view.php?ud=202606231818398641e7e8286d56_1",
          "pubDate": "Tue, 23 Jun 2026 18:24:00 +0900",
          "pubTimestamp": 1782206640000,
          "sourceName": "G-ENEWS"
        },
        {
          "title": "외식·음료·주류 ‘가격 줄인상’에 소비자 ‘한숨’",
          "link": "https://www.busan.com/view/busan/view.php?code=2026062318222177123",
          "pubDate": "Tue, 23 Jun 2026 18:23:00 +0900",
          "pubTimestamp": 1782206580000,
          "sourceName": "BUSAN"
        },
        {
          "title": "고려아연, 글로벌 ESG 올 1등급에 실적까지…‘핵심광물 대장株’ 재부...",
          "link": "https://www.news2day.co.kr/article/20260623500257",
          "pubDate": "Tue, 23 Jun 2026 18:22:00 +0900",
          "pubTimestamp": 1782206520000,
          "sourceName": "NEWS2DAY"
        },
        {
          "title": "마이크론, 기술주 약세·중동 불안도 비껴갔다…사상 최고가 경신",
          "link": "http://coinreaders.com/243969",
          "pubDate": "Tue, 23 Jun 2026 18:20:00 +0900",
          "pubTimestamp": 1782206400000,
          "sourceName": "COINREADERS"
        },
        {
          "title": "글로벌 VC 통해 신약개발~사업화… 바이오 '뉴코' 바람",
          "link": "http://www.fnnews.com/news/202606231817379164",
          "pubDate": "Tue, 23 Jun 2026 18:19:00 +0900",
          "pubTimestamp": 1782206340000,
          "sourceName": "파이낸셜뉴스"
        },
        {
          "title": "\"공구우먼에서 나인앤컴퍼니로 새출발\" 글로벌 사업 다각화",
          "link": "http://www.fnnews.com/news/202606231608315845",
          "pubDate": "Tue, 23 Jun 2026 18:18:00 +0900",
          "pubTimestamp": 1782206280000,
          "sourceName": "파이낸셜뉴스"
        }
      ]
    },
    "policy": {
      "name": "금융정책",
      "queries": [
        "한국은행 금리",
        "기준금리 인상",
        "통화정책",
        "금융위원회",
        "기획재정부"
      ],
      "news": [
        {
          "title": "자사주 투명성 강화, 모든 상장회사 공시 의무 확대",
          "link": "https://www.tokenpost.kr/news/economy/372095",
          "pubDate": "Tue, 23 Jun 2026 19:34:00 +0900",
          "pubTimestamp": 1782210840000,
          "sourceName": "TOKENPOST"
        },
        {
          "title": "[포커스] KB국민은행, 2분기 실적반등 기대…'리딩뱅크' 경쟁 가열",
          "link": "https://www.startuptoday.co.kr/news/articleView.html?idxno=804379",
          "pubDate": "Tue, 23 Jun 2026 19:30:00 +0900",
          "pubTimestamp": 1782210600000,
          "sourceName": "STARTUPTODAY"
        },
        {
          "title": "포스코인터내셔널, 창사 첫 글로벌본드 발행 성공",
          "link": "https://www.hidomin.com/news/articleView.html?idxno=710580",
          "pubDate": "Tue, 23 Jun 2026 19:22:00 +0900",
          "pubTimestamp": 1782210120000,
          "sourceName": "HIDOMIN"
        },
        {
          "title": "\"연준, 올해 금리 3차례 인상 가능\"…달라진 월가 전망",
          "link": "https://www.newsis.com/view/NISX20260623_0003680690",
          "pubDate": "Tue, 23 Jun 2026 19:20:00 +0900",
          "pubTimestamp": 1782210000000,
          "sourceName": "뉴시스"
        },
        {
          "title": "머니무브 가속화에 저축은행 수신 경쟁 '후끈'…연 4% 예금 늘린다",
          "link": "https://www.thepublic.kr/news/articleView.html?idxno=308797",
          "pubDate": "Tue, 23 Jun 2026 19:18:00 +0900",
          "pubTimestamp": 1782209880000,
          "sourceName": "THEPUBLIC"
        },
        {
          "title": "코스피 '검은 화요일'...외국인·기관 투매로 역대 최대 910.71포인트 하...",
          "link": "https://www.livebiz.today/news/articleView.html?idxno=202817",
          "pubDate": "Tue, 23 Jun 2026 19:14:00 +0900",
          "pubTimestamp": 1782209640000,
          "sourceName": "LIVEBIZ"
        },
        {
          "title": "\"사후 감독 아닌 상시검증\"… 금융 AI 규제 전환 필요성 제기",
          "link": "https://www.insnews.co.kr/news/articleView.html?idxno=91464",
          "pubDate": "Tue, 23 Jun 2026 19:14:00 +0900",
          "pubTimestamp": 1782209640000,
          "sourceName": "INSNEWS"
        },
        {
          "title": "6월 전북지역 소비자심리지수 소폭 상승",
          "link": "https://sjbnews.com/news/news.php?number=881339",
          "pubDate": "Tue, 23 Jun 2026 19:03:00 +0900",
          "pubTimestamp": 1782208980000,
          "sourceName": "SJBNEWS"
        },
        {
          "title": "금융위 세종 이전 논의 '솔솔'… 충청권 금융허브 꿈틀",
          "link": "https://www.daejonilbo.com/news/articleView.html?idxno=2283453",
          "pubDate": "Tue, 23 Jun 2026 19:03:00 +0900",
          "pubTimestamp": 1782208980000,
          "sourceName": "DAEJONILBO"
        },
        {
          "title": "황성엽 \"전 국민 투자 과열 건강하지 않아…연금·ISA 중심 시장 가야\"",
          "link": "http://www.metroseoul.co.kr/article/20260623500482",
          "pubDate": "Tue, 23 Jun 2026 19:00:00 +0900",
          "pubTimestamp": 1782208800000,
          "sourceName": "METROSEOUL"
        },
        {
          "title": "리플, 룩셈부르크 예비 승인 확보…XRP는 1달러 지지선 시험대",
          "link": "https://www.tokenpost.kr/news/cryptocurrency/372080",
          "pubDate": "Tue, 23 Jun 2026 18:54:00 +0900",
          "pubTimestamp": 1782208440000,
          "sourceName": "TOKENPOST"
        },
        {
          "title": "[은행 이모저모] 국민은행·경남은행·광주은행 등",
          "link": "http://www.bizwnews.com/news/articleView.html?idxno=139259",
          "pubDate": "Tue, 23 Jun 2026 18:52:00 +0900",
          "pubTimestamp": 1782208320000,
          "sourceName": "BIZWNEWS"
        },
        {
          "title": "하나금융, 취업교육 및 고용연계 지원 사업 실시 外",
          "link": "https://www.rcast.co.kr/news/articleView.html?idxno=31104",
          "pubDate": "Tue, 23 Jun 2026 18:46:00 +0900",
          "pubTimestamp": 1782207960000,
          "sourceName": "RCAST"
        },
        {
          "title": "['클릭' 증시] 애써 키운 코스피 무너뜨리는 한국 정치",
          "link": "http://www.00news.co.kr/news/articleView.html?idxno=104647",
          "pubDate": "Tue, 23 Jun 2026 18:46:00 +0900",
          "pubTimestamp": 1782207960000,
          "sourceName": "00NEWS"
        },
        {
          "title": "트리니티항공, 잇단 재무구조 개선 움직임…소노인터내셔널, IPO 재도전...",
          "link": "http://www.newsdream.kr/news/articleView.html?idxno=113483",
          "pubDate": "Tue, 23 Jun 2026 18:46:00 +0900",
          "pubTimestamp": 1782207960000,
          "sourceName": "NEWSDREAM"
        },
        {
          "title": "[현장] \"금융분야 AI 도입은 시간문제…관건은 규제의 수준\"",
          "link": "http://www.sisafocus.co.kr/news/articleView.html?idxno=361733",
          "pubDate": "Tue, 23 Jun 2026 18:46:00 +0900",
          "pubTimestamp": 1782207960000,
          "sourceName": "SISAFOCUS"
        },
        {
          "title": "황성엽 금투협회장 \"과열된 증시, 자정 노력해야…개인보다 기관 중심으...",
          "link": "https://www.ebn.co.kr/news/articleView.html?idxno=1713633",
          "pubDate": "Tue, 23 Jun 2026 18:44:00 +0900",
          "pubTimestamp": 1782207840000,
          "sourceName": "EBN"
        },
        {
          "title": "[치솟는 국채금리] WGBI 효과도 역부족…가계·기업 짓누른다",
          "link": "https://www.ajunews.com/view/20260623145532364",
          "pubDate": "Tue, 23 Jun 2026 18:32:00 +0900",
          "pubTimestamp": 1782207120000,
          "sourceName": "AJUNEWS"
        },
        {
          "title": "[치솟는 국채금리] 전 구간 '4% 시대' 오나 …물가·AI發 '고금리 뉴노멀...",
          "link": "https://www.ajunews.com/view/20260623140920204",
          "pubDate": "Tue, 23 Jun 2026 18:32:00 +0900",
          "pubTimestamp": 1782207120000,
          "sourceName": "AJUNEWS"
        },
        {
          "title": "홍진표 대표가 밝힌 급변하는 원화 스테이블 코인 시장을 앞둔 마브렉스...",
          "link": "https://gamefocus.co.kr/detail.php?number=176898",
          "pubDate": "Tue, 23 Jun 2026 18:30:00 +0900",
          "pubTimestamp": 1782207000000,
          "sourceName": "GAMEFOCUS"
        },
        {
          "title": "올해 자사주 소각 5개월새 43조…금융위, 모든 보유 상장사 공시 강화",
          "link": "https://www.mk.co.kr/article/12081200",
          "pubDate": "Tue, 23 Jun 2026 18:28:00 +0900",
          "pubTimestamp": 1782206880000,
          "sourceName": "매일경제"
        },
        {
          "title": "“집값·임금 다 오를 것”…성과급 풍년에 소비자 전망지수 치솟아",
          "link": "https://www.donga.com/news/Economy/article/all/20260623/134166214/1",
          "pubDate": "Tue, 23 Jun 2026 18:27:00 +0900",
          "pubTimestamp": 1782206820000,
          "sourceName": "동아일보"
        },
        {
          "title": "코스피 하루 만에 910포인트 증발…역대 최대 하락폭 기록하며 8200선 턱...",
          "link": "https://www.industrynews.co.kr/news/articleView.html?idxno=82481",
          "pubDate": "Tue, 23 Jun 2026 18:26:00 +0900",
          "pubTimestamp": 1782206760000,
          "sourceName": "INDUSTRYNEWS"
        },
        {
          "title": "주식 팔면 이틀 묶이는 매도대금… 당국, 하루로 단축 추진",
          "link": "https://it.chosun.com/news/articleView.html?idxno=2023092164435",
          "pubDate": "Tue, 23 Jun 2026 18:26:00 +0900",
          "pubTimestamp": 1782206760000,
          "sourceName": "IT"
        },
        {
          "title": "금융위, 망분리 확대 요구에 신중… \"성공사례 축적부터\"",
          "link": "https://it.chosun.com/news/articleView.html?idxno=2023092164434",
          "pubDate": "Tue, 23 Jun 2026 18:26:00 +0900",
          "pubTimestamp": 1782206760000,
          "sourceName": "IT"
        },
        {
          "title": "광주은행·케이뱅크, 중·저신용자 공동 금융상품 개발 협력",
          "link": "http://www.whitepaper.co.kr/news/articleView.html?idxno=263797",
          "pubDate": "Tue, 23 Jun 2026 18:26:00 +0900",
          "pubTimestamp": 1782206760000,
          "sourceName": "WHITEPAPER"
        },
        {
          "title": "단일종목 레버리지 25% 급락에…당국, 안전장치 마련 검토",
          "link": "http://www.yonhapnewstv.co.kr/news/AKR20260623182450S1g",
          "pubDate": "Tue, 23 Jun 2026 18:25:00 +0900",
          "pubTimestamp": 1782206700000,
          "sourceName": "YONHAPNEWSTV"
        },
        {
          "title": "도내 6월 소비자심리지수 2.0p 상승··· 금리-집값전망↑",
          "link": "http://www.jjn.co.kr/news/articleView.html?idxno=1044508",
          "pubDate": "Tue, 23 Jun 2026 18:24:00 +0900",
          "pubTimestamp": 1782206640000,
          "sourceName": "JJN"
        },
        {
          "title": "광주·전남 소비자심리 두 달 연속 개선 흐름",
          "link": "http://www.jndn.com/article.php?aid=1782206420434826095",
          "pubDate": "Tue, 23 Jun 2026 18:24:00 +0900",
          "pubTimestamp": 1782206640000,
          "sourceName": "JNDN"
        },
        {
          "title": "모태펀드와 국민성장펀드, 벤처 스타트업에 대규모 후속 자금 연결",
          "link": "https://www.tokenpost.kr/news/policy/372071",
          "pubDate": "Tue, 23 Jun 2026 18:24:00 +0900",
          "pubTimestamp": 1782206640000,
          "sourceName": "TOKENPOST"
        }
      ]
    },
    "crypto": {
      "name": "암호화폐",
      "queries": [
        "비트코인",
        "이더리움",
        "가상화폐",
        "알트코인"
      ],
      "news": [
        {
          "title": "두쥔 \"블록체인, 금융 인프라 재편할 것…가상자산 투자 지속\"",
          "link": "https://www.tokenpost.kr/news/breaking/372092",
          "pubDate": "Tue, 23 Jun 2026 19:26:00 +0900",
          "pubTimestamp": 1782210360000,
          "sourceName": "TOKENPOST"
        },
        {
          "title": "비트코인 6만2000달러로 후퇴…양자컴퓨팅·ETF 유출에 시장 변동성 확대",
          "link": "https://www.tokenpost.kr/news/cryptocurrency/372090",
          "pubDate": "Tue, 23 Jun 2026 19:24:00 +0900",
          "pubTimestamp": 1782210240000,
          "sourceName": "TOKENPOST"
        },
        {
          "title": "리플, 룩셈부르크 예비 승인 확보…XRP는 1달러 지지선 시험대",
          "link": "https://www.tokenpost.kr/news/cryptocurrency/372080",
          "pubDate": "Tue, 23 Jun 2026 18:54:00 +0900",
          "pubTimestamp": 1782208440000,
          "sourceName": "TOKENPOST"
        },
        {
          "title": "리플(XRP), 유럽 전역 서비스 확대 발판 마련…룩셈부르크서 가상자산 ...",
          "link": "https://www.cbci.co.kr/news/articleView.html?idxno=584079",
          "pubDate": "Tue, 23 Jun 2026 18:48:00 +0900",
          "pubTimestamp": 1782208080000,
          "sourceName": "CBCI"
        },
        {
          "title": "이더리움(ETH), ETF 7주 연속 자금 탈출...예치 대기열은 12배 폭발",
          "link": "http://coinreaders.com/243977",
          "pubDate": "Tue, 23 Jun 2026 18:46:00 +0900",
          "pubTimestamp": 1782207960000,
          "sourceName": "COINREADERS"
        },
        {
          "title": "[게임뉴스] 넥써쓰 및 비피엠지 소식 외",
          "link": "https://www.gamevu.co.kr/news/articleView.html?idxno=58874",
          "pubDate": "Tue, 23 Jun 2026 18:44:00 +0900",
          "pubTimestamp": 1782207840000,
          "sourceName": "GAMEVU"
        },
        {
          "title": "비트코인 수이세, MiCAR 라이선스 확보…유럽 시장 공략 본격화",
          "link": "https://www.tokenpost.kr/news/policy/372079",
          "pubDate": "Tue, 23 Jun 2026 18:44:00 +0900",
          "pubTimestamp": 1782207840000,
          "sourceName": "TOKENPOST"
        },
        {
          "title": "바로톡, Web3·전문 산업 행사 위한 차세대 AI 통역 솔루션 제공",
          "link": "https://www.tokenpost.kr/news/insights/372077",
          "pubDate": "Tue, 23 Jun 2026 18:42:00 +0900",
          "pubTimestamp": 1782207720000,
          "sourceName": "TOKENPOST"
        },
        {
          "title": "리차드 텅 바이낸스 CEO, 스테이블코인 주식 관련 거래와 파생상품 결제...",
          "link": "http://www.hansbiz.co.kr/news/articleView.html?idxno=845789",
          "pubDate": "Tue, 23 Jun 2026 18:30:00 +0900",
          "pubTimestamp": 1782207000000,
          "sourceName": "HANSBIZ"
        },
        {
          "title": "비트코인 하루 만에 6만5,000달러→6만2,000달러…암호화폐 시장 다시 흔...",
          "link": "http://coinreaders.com/243967",
          "pubDate": "Tue, 23 Jun 2026 18:16:00 +0900",
          "pubTimestamp": 1782206160000,
          "sourceName": "COINREADERS"
        },
        {
          "title": "비트코인·이더리움 급락…5억8000만 달러 롱 청산에 ETF 유출까지",
          "link": "https://www.tokenpost.kr/news/cryptocurrency/372069",
          "pubDate": "Tue, 23 Jun 2026 18:14:00 +0900",
          "pubTimestamp": 1782206040000,
          "sourceName": "TOKENPOST"
        },
        {
          "title": "이더리움 고래, 5만 ETH 숏 포지션서 435만달러 미실현 수익",
          "link": "https://www.tokenpost.kr/news/breaking/372070",
          "pubDate": "Tue, 23 Jun 2026 18:14:00 +0900",
          "pubTimestamp": 1782206040000,
          "sourceName": "TOKENPOST"
        },
        {
          "title": "6월 23일 퇴근길 팟캐스트 21억달러 청산 충격, 롱 베팅 붕괴와 ETF 순유...",
          "link": "https://www.tokenpost.kr/news/insights/372051",
          "pubDate": "Tue, 23 Jun 2026 17:54:00 +0900",
          "pubTimestamp": 1782204840000,
          "sourceName": "TOKENPOST"
        },
        {
          "title": "美상원, 2030년까지 CBDC 발행금지법 가결…스테이블코인 힘 실린다",
          "link": "https://www.edaily.co.kr/news/newspath.asp?newsid=05077446645484672",
          "pubDate": "Tue, 23 Jun 2026 17:53:00 +0900",
          "pubTimestamp": 1782204780000,
          "sourceName": "이데일리"
        },
        {
          "title": "블록체인 기반 TCG 온보딩, 넥써쓰-머스타버스 MOU 체결",
          "link": "https://www.gamemeca.com/mv.php?inflow=naver_s&gid=1776879",
          "pubDate": "Tue, 23 Jun 2026 17:53:00 +0900",
          "pubTimestamp": 1782204780000,
          "sourceName": "GAMEMECA"
        },
        {
          "title": "비트코인(BTC)·스테이블코인·스트래티지(MSTR), 기관 자금 80억 달러 이...",
          "link": "http://coinreaders.com/243959",
          "pubDate": "Tue, 23 Jun 2026 17:52:00 +0900",
          "pubTimestamp": 1782204720000,
          "sourceName": "COINREADERS"
        },
        {
          "title": "넥써쓰, 웹3 TCG '아우라얄' · 수집형 RPG '미스 레전드' 크로쓰 온보딩",
          "link": "http://www.worktoday.co.kr/news/articleView.html?idxno=85951",
          "pubDate": "Tue, 23 Jun 2026 17:48:00 +0900",
          "pubTimestamp": 1782204480000,
          "sourceName": "WORKTODAY"
        },
        {
          "title": "BTC 단기 보유자 자본 56% 감소…장기 보유자 이탈은 제한적",
          "link": "https://www.tokenpost.kr/news/breaking/372062",
          "pubDate": "Tue, 23 Jun 2026 17:46:00 +0900",
          "pubTimestamp": 1782204360000,
          "sourceName": "TOKENPOST"
        },
        {
          "title": "탈중앙화 상징 '디지털 금' 비트코인…이젠 금융자산에 더 가깝다",
          "link": "https://news.mtn.co.kr/news-detail/2026062316221031303",
          "pubDate": "Tue, 23 Jun 2026 17:38:00 +0900",
          "pubTimestamp": 1782203880000,
          "sourceName": "NEWS"
        },
        {
          "title": "넥써쓰, 대만 머스타버스 '아우라얄' 크로쓰 온보딩…글로벌 확장",
          "link": "https://www.shinailbo.co.kr/news/articleView.html?idxno=5033550",
          "pubDate": "Tue, 23 Jun 2026 17:38:00 +0900",
          "pubTimestamp": 1782203880000,
          "sourceName": "SHINAILBO"
        },
        {
          "title": "'코인개미' 1년 새  90만명 감소 ... 거래대금은 '반토막'",
          "link": "http://www.queen.co.kr/news/articleView.html?idxno=459120",
          "pubDate": "Tue, 23 Jun 2026 17:36:00 +0900",
          "pubTimestamp": 1782203760000,
          "sourceName": "QUEEN"
        },
        {
          "title": "루마니아 병원들, 해커 공격에 아날로그 방식으로 대처",
          "link": "https://www.hankyung.com/article/2026062334167",
          "pubDate": "Tue, 23 Jun 2026 17:30:00 +0900",
          "pubTimestamp": 1782203400000,
          "sourceName": "한국경제"
        },
        {
          "title": "장부가치 수십억 증발…가상자산 폭락에 발목 잡힌 게임사 '재무 비상'",
          "link": "https://www.thepublic.kr/news/articleView.html?idxno=308734",
          "pubDate": "Tue, 23 Jun 2026 17:30:00 +0900",
          "pubTimestamp": 1782203400000,
          "sourceName": "THEPUBLIC"
        },
        {
          "title": "'24시간 주식거래' 통했다…주식토큰 시장, 올해 130% 급성장",
          "link": "https://www.news1.kr/finance/blockchain-fintech/6205973",
          "pubDate": "Tue, 23 Jun 2026 17:29:00 +0900",
          "pubTimestamp": 1782203340000,
          "sourceName": "뉴스1"
        },
        {
          "title": "안도걸 “원화 스테이블코인 제도화 속도…여의치 않으면 단독 원 구성...",
          "link": "https://www.etoday.co.kr/news/view/2596482",
          "pubDate": "Tue, 23 Jun 2026 17:26:00 +0900",
          "pubTimestamp": 1782203160000,
          "sourceName": "ETODAY"
        },
        {
          "title": "넥써쓰, 크로쓰에 대만 TCG 들어왔다",
          "link": "https://www.gametoc.co.kr/news/articleView.html?idxno=109465",
          "pubDate": "Tue, 23 Jun 2026 17:20:00 +0900",
          "pubTimestamp": 1782202800000,
          "sourceName": "GAMETOC"
        },
        {
          "title": "MyTonWallet, ‘마이 월렛’으로 리브랜딩…11개 체인 통합 지갑 경쟁 본...",
          "link": "https://www.tokenpost.kr/news/tech/372054",
          "pubDate": "Tue, 23 Jun 2026 17:14:00 +0900",
          "pubTimestamp": 1782202440000,
          "sourceName": "TOKENPOST"
        },
        {
          "title": "[데일리픽] 비트코인, 부동산처럼 장기 보유해라…中, 美 희토류·방산...",
          "link": "https://www.digitaltoday.co.kr/news/articleView.html?idxno=677518",
          "pubDate": "Tue, 23 Jun 2026 17:06:00 +0900",
          "pubTimestamp": 1782201960000,
          "sourceName": "DIGITALTODAY"
        },
        {
          "title": "안도걸 의원 \"스테이블코인, 미래 금융 인프라 핵심…하반기 입법 추진...",
          "link": "https://www.asiatoday.co.kr/kn/view.php?key=20260623010008143",
          "pubDate": "Tue, 23 Jun 2026 16:50:00 +0900",
          "pubTimestamp": 1782201000000,
          "sourceName": "ASIATODAY"
        },
        {
          "title": "리플(XRP) 방향성 탐색...추가 조정 가능성도",
          "link": "https://www.cbci.co.kr/news/articleView.html?idxno=584043",
          "pubDate": "Tue, 23 Jun 2026 16:46:00 +0900",
          "pubTimestamp": 1782200760000,
          "sourceName": "CBCI"
        }
      ]
    }
  }
}